windflow/__init__.py
windflow/_version.py
windflow/loop.py
windflow/settings.py
windflow/utils.py
windflow/commands/__init__.py
windflow/commands/base.py
windflow/commands/mixins.py
windflow/commands/server.py
windflow/models/__init__.py
windflow/models/mixins.py
windflow/models/utils.py
windflow/services/__init__.py
windflow/services/assets.py
windflow/services/base.py
windflow/services/cli.py
windflow/services/db.py
windflow/services/templating.py
windflow/web/__init__.py
windflow/web/application.py
windflow/web/handler.py
windflow/web/helpers.py
windflow/web/package.py
windflow-0.2.0.dist-info/METADATA
windflow-0.2.0.dist-info/RECORD
windflow-0.2.0.dist-info/WHEEL
windflow-0.2.0.dist-info/top_level.txt
